{"moduleDefinition":{"range":[1,1,1,45],"value":{"type":"normal","normal":{"moduleName":{"range":[1,8,1,31],"value":["EveOnline","MemoryReading"]},"exposingList":{"range":[1,32,1,45],"value":{"type":"all","all":[1,42,1,44]}}}}},"imports":[{"range":[3,1,3,12],"value":{"moduleName":{"range":[3,8,3,12],"value":["Dict"]},"moduleAlias":null,"exposingList":null}},{"range":[4,1,4,19],"value":{"moduleName":{"range":[4,8,4,19],"value":["Json","Decode"]},"moduleAlias":null,"exposingList":null}},{"range":[5,1,5,19],"value":{"moduleName":{"range":[5,8,5,19],"value":["Json","Encode"]},"moduleAlias":null,"exposingList":null}}],"declarations":[{"range":[8,1,14,6],"value":{"type":"typeAlias","typeAlias":{"documentation":null,"name":{"range":[8,12,8,22],"value":"UITreeNode"},"generics":[],"typeAnnotation":{"range":[9,5,14,6],"value":{"type":"record","record":{"value":[{"range":[9,7,9,39],"value":{"name":{"range":[9,7,9,19],"value":"originalJson"},"typeAnnotation":{"range":[9,22,9,39],"value":{"type":"typed","typed":{"moduleNameAndName":{"range":[9,22,9,39],"value":{"moduleName":["Json","Encode"],"name":"Value"}},"args":[]}}}}},{"range":[10,5,11,5],"value":{"name":{"range":[10,7,10,26],"value":"pythonObjectAddress"},"typeAnnotation":{"range":[10,29,10,35],"value":{"type":"typed","typed":{"moduleNameAndName":{"range":[10,29,10,35],"value":{"moduleName":[],"name":"String"}},"args":[]}}}}},{"range":[11,5,12,5],"value":{"name":{"range":[11,7,11,27],"value":"pythonObjectTypeName"},"typeAnnotation":{"range":[11,30,11,36],"value":{"type":"typed","typed":{"moduleNameAndName":{"range":[11,30,11,36],"value":{"moduleName":[],"name":"String"}},"args":[]}}}}},{"range":[12,5,13,5],"value":{"name":{"range":[12,7,12,28],"value":"dictEntriesOfInterest"},"typeAnnotation":{"range":[12,31,12,65],"value":{"type":"typed","typed":{"moduleNameAndName":{"range":[12,31,12,40],"value":{"moduleName":["Dict"],"name":"Dict"}},"args":[{"range":[12,41,12,47],"value":{"type":"typed","typed":{"moduleNameAndName":{"range":[12,41,12,47],"value":{"moduleName":[],"name":"String"}},"args":[]}}},{"range":[12,48,12,65],"value":{"type":"typed","typed":{"moduleNameAndName":{"range":[12,48,12,65],"value":{"moduleName":["Json","Encode"],"name":"Value"}},"args":[]}}}]}}}}},{"range":[13,5,14,5],"value":{"name":{"range":[13,7,13,15],"value":"children"},"typeAnnotation":{"range":[13,18,13,46],"value":{"type":"typed","typed":{"moduleNameAndName":{"range":[13,18,13,23],"value":{"moduleName":[],"name":"Maybe"}},"args":[{"range":[13,24,13,46],"value":{"type":"typed","typed":{"moduleNameAndName":{"range":[13,25,13,29],"value":{"moduleName":[],"name":"List"}},"args":[{"range":[13,30,13,45],"value":{"type":"typed","typed":{"moduleNameAndName":{"range":[13,30,13,45],"value":{"moduleName":[],"name":"UITreeNodeChild"}},"args":[]}}}]}}}]}}}}}]}}}}}},{"range":[17,1,18,33],"value":{"type":"typedecl","typedecl":{"documentation":null,"name":{"range":[17,6,17,21],"value":"UITreeNodeChild"},"generics":[],"constructors":[{"range":[18,7,18,33],"value":{"name":{"range":[18,7,18,22],"value":"UITreeNodeChild"},"arguments":[{"range":[18,23,18,33],"value":{"type":"typed","typed":{"moduleNameAndName":{"range":[18,23,18,33],"value":{"moduleName":[],"name":"UITreeNode"}},"args":[]}}}]}}]}}},{"range":[21,1,25,17],"value":{"type":"function","function":{"documentation":null,"signature":{"range":[21,1,21,54],"value":{"name":{"range":[21,1,21,22],"value":"unwrapUITreeNodeChild"},"typeAnnotation":{"range":[21,25,21,54],"value":{"type":"function","function":{"left":{"range":[21,25,21,40],"value":{"type":"typed","typed":{"moduleNameAndName":{"range":[21,25,21,40],"value":{"moduleName":[],"name":"UITreeNodeChild"}},"args":[]}}},"right":{"range":[21,44,21,54],"value":{"type":"typed","typed":{"moduleNameAndName":{"range":[21,44,21,54],"value":{"moduleName":[],"name":"UITreeNode"}},"args":[]}}}}}}}},"declaration":{"range":[22,1,25,17],"value":{"name":{"range":[22,1,22,22],"value":"unwrapUITreeNodeChild"},"arguments":[{"range":[22,23,22,28],"value":{"type":"var","var":{"value":"child"}}}],"expression":{"range":[23,5,25,17],"value":{"type":"case","case":{"cases":[{"pattern":{"range":[24,9,24,29],"value":{"type":"named","named":{"qualified":{"moduleName":[],"name":"UITreeNodeChild"},"patterns":[{"range":[24,25,24,29],"value":{"type":"var","var":{"value":"node"}}}]}}},"expression":{"range":[25,13,25,17],"value":{"type":"functionOrValue","functionOrValue":{"moduleName":[],"name":"node"}}}}],"expression":{"range":[23,10,23,15],"value":{"type":"functionOrValue","functionOrValue":{"moduleName":[],"name":"child"}}}}}}}}}}},{"range":[28,1,34,20],"value":{"type":"function","function":{"documentation":null,"signature":{"range":[28,1,28,49],"value":{"name":{"range":[28,1,28,29],"value":"countDescendantsInUITreeNode"},"typeAnnotation":{"range":[28,32,28,49],"value":{"type":"function","function":{"left":{"range":[28,32,28,42],"value":{"type":"typed","typed":{"moduleNameAndName":{"range":[28,32,28,42],"value":{"moduleName":[],"name":"UITreeNode"}},"args":[]}}},"right":{"range":[28,46,28,49],"value":{"type":"typed","typed":{"moduleNameAndName":{"range":[28,46,28,49],"value":{"moduleName":[],"name":"Int"}},"args":[]}}}}}}}},"declaration":{"range":[29,1,34,20],"value":{"name":{"range":[29,1,29,29],"value":"countDescendantsInUITreeNode"},"arguments":[{"range":[29,30,29,36],"value":{"type":"var","var":{"value":"parent"}}}],"expression":{"range":[30,11,34,20],"value":{"type":"application","application":[{"range":[30,11,30,20],"value":{"type":"recordAccess","recordAccess":{"expression":{"range":[30,5,30,11],"value":{"type":"functionOrValue","functionOrValue":{"moduleName":[],"name":"parent"}}},"name":{"range":[30,12,30,20],"value":"children"}}}},{"range":[31,9,31,11],"value":{"type":"operator","operator":"|>"}},{"range":[31,12,31,29],"value":{"type":"functionOrValue","functionOrValue":{"moduleName":["Maybe"],"name":"withDefault"}}},{"range":[31,30,31,32],"value":{"type":"list","list":[]}},{"range":[32,9,32,11],"value":{"type":"operator","operator":"|>"}},{"range":[32,12,32,20],"value":{"type":"functionOrValue","functionOrValue":{"moduleName":["List"],"name":"map"}}},{"range":[32,21,32,42],"value":{"type":"functionOrValue","functionOrValue":{"moduleName":[],"name":"unwrapUITreeNodeChild"}}},{"range":[33,9,33,11],"value":{"type":"operator","operator":"|>"}},{"range":[33,12,33,20],"value":{"type":"functionOrValue","functionOrValue":{"moduleName":["List"],"name":"map"}}},{"range":[33,21,33,60],"value":{"type":"parenthesized","parenthesized":{"range":[33,22,33,59],"value":{"type":"application","application":[{"range":[33,22,33,50],"value":{"type":"functionOrValue","functionOrValue":{"moduleName":[],"name":"countDescendantsInUITreeNode"}}},{"range":[33,51,33,53],"value":{"type":"operator","operator":">>"}},{"range":[33,54,33,57],"value":{"type":"prefixoperator","prefixoperator":"+"}},{"range":[33,58,33,59],"value":{"type":"integer","integer":1}}]}}}},{"range":[34,9,34,11],"value":{"type":"operator","operator":"|>"}},{"range":[34,12,34,20],"value":{"type":"functionOrValue","functionOrValue":{"moduleName":["List"],"name":"sum"}}}]}}}}}}},{"range":[37,1,42,81],"value":{"type":"function","function":{"documentation":null,"signature":{"range":[37,1,37,60],"value":{"name":{"range":[37,1,37,28],"value":"listDescendantsInUITreeNode"},"typeAnnotation":{"range":[37,31,37,60],"value":{"type":"function","function":{"left":{"range":[37,31,37,41],"value":{"type":"typed","typed":{"moduleNameAndName":{"range":[37,31,37,41],"value":{"moduleName":[],"name":"UITreeNode"}},"args":[]}}},"right":{"range":[37,45,37,60],"value":{"type":"typed","typed":{"moduleNameAndName":{"range":[37,45,37,49],"value":{"moduleName":[],"name":"List"}},"args":[{"range":[37,50,37,60],"value":{"type":"typed","typed":{"moduleNameAndName":{"range":[37,50,37,60],"value":{"moduleName":[],"name":"UITreeNode"}},"args":[]}}}]}}}}}}}},"declaration":{"range":[38,1,42,81],"value":{"name":{"range":[38,1,38,28],"value":"listDescendantsInUITreeNode"},"arguments":[{"range":[38,29,38,35],"value":{"type":"var","var":{"value":"parent"}}}],"expression":{"range":[39,11,42,81],"value":{"type":"application","application":[{"range":[39,11,39,20],"value":{"type":"recordAccess","recordAccess":{"expression":{"range":[39,5,39,11],"value":{"type":"functionOrValue","functionOrValue":{"moduleName":[],"name":"parent"}}},"name":{"range":[39,12,39,20],"value":"children"}}}},{"range":[40,9,40,11],"value":{"type":"operator","operator":"|>"}},{"range":[40,12,40,29],"value":{"type":"functionOrValue","functionOrValue":{"moduleName":["Maybe"],"name":"withDefault"}}},{"range":[40,30,40,32],"value":{"type":"list","list":[]}},{"range":[41,9,41,11],"value":{"type":"operator","operator":"|>"}},{"range":[41,12,41,20],"value":{"type":"functionOrValue","functionOrValue":{"moduleName":["List"],"name":"map"}}},{"range":[41,21,41,42],"value":{"type":"functionOrValue","functionOrValue":{"moduleName":[],"name":"unwrapUITreeNodeChild"}}},{"range":[42,9,42,11],"value":{"type":"operator","operator":"|>"}},{"range":[42,12,42,26],"value":{"type":"functionOrValue","functionOrValue":{"moduleName":["List"],"name":"concatMap"}}},{"range":[42,27,42,81],"value":{"type":"parenthesized","parenthesized":{"range":[42,28,42,80],"value":{"type":"lambda","lambda":{"patterns":[{"range":[42,29,42,34],"value":{"type":"var","var":{"value":"child"}}}],"expression":{"range":[42,38,42,80],"value":{"type":"application","application":[{"range":[42,38,42,43],"value":{"type":"functionOrValue","functionOrValue":{"moduleName":[],"name":"child"}}},{"range":[42,44,42,46],"value":{"type":"operator","operator":"::"}},{"range":[42,47,42,74],"value":{"type":"functionOrValue","functionOrValue":{"moduleName":[],"name":"listDescendantsInUITreeNode"}}},{"range":[42,75,42,80],"value":{"type":"functionOrValue","functionOrValue":{"moduleName":[],"name":"child"}}}]}}}}}}}]}}}}}}},{"range":[45,1,47,47],"value":{"type":"function","function":{"documentation":null,"signature":{"range":[45,1,45,78],"value":{"name":{"range":[45,1,45,30],"value":"decodeMemoryReadingFromString"},"typeAnnotation":{"range":[45,33,45,78],"value":{"type":"function","function":{"left":{"range":[45,33,45,39],"value":{"type":"typed","typed":{"moduleNameAndName":{"range":[45,33,45,39],"value":{"moduleName":[],"name":"String"}},"args":[]}}},"right":{"range":[45,43,45,78],"value":{"type":"typed","typed":{"moduleNameAndName":{"range":[45,43,45,49],"value":{"moduleName":[],"name":"Result"}},"args":[{"range":[45,50,45,67],"value":{"type":"typed","typed":{"moduleNameAndName":{"range":[45,50,45,67],"value":{"moduleName":["Json","Decode"],"name":"Error"}},"args":[]}}},{"range":[45,68,45,78],"value":{"type":"typed","typed":{"moduleNameAndName":{"range":[45,68,45,78],"value":{"moduleName":[],"name":"UITreeNode"}},"args":[]}}}]}}}}}}}},"declaration":{"range":[46,1,47,47],"value":{"name":{"range":[46,1,46,30],"value":"decodeMemoryReadingFromString"},"arguments":[],"expression":{"range":[47,5,47,47],"value":{"type":"application","application":[{"range":[47,5,47,29],"value":{"type":"functionOrValue","functionOrValue":{"moduleName":["Json","Decode"],"name":"decodeString"}}},{"range":[47,30,47,47],"value":{"type":"functionOrValue","functionOrValue":{"moduleName":[],"name":"uiTreeNodeDecoder"}}}]}}}}}}},{"range":[50,1,65,111],"value":{"type":"function","function":{"documentation":null,"signature":{"range":[50,1,50,51],"value":{"name":{"range":[50,1,50,18],"value":"uiTreeNodeDecoder"},"typeAnnotation":{"range":[50,21,50,51],"value":{"type":"typed","typed":{"moduleNameAndName":{"range":[50,21,50,40],"value":{"moduleName":["Json","Decode"],"name":"Decoder"}},"args":[{"range":[50,41,50,51],"value":{"type":"typed","typed":{"moduleNameAndName":{"range":[50,41,50,51],"value":{"moduleName":[],"name":"UITreeNode"}},"args":[]}}}]}}}}},"declaration":{"range":[51,1,65,111],"value":{"name":{"range":[51,1,51,18],"value":"uiTreeNodeDecoder"},"arguments":[],"expression":{"range":[52,5,65,111],"value":{"type":"application","application":[{"range":[52,5,52,21],"value":{"type":"functionOrValue","functionOrValue":{"moduleName":["Json","Decode"],"name":"map5"}}},{"range":[53,9,60,10],"value":{"type":"parenthesized","parenthesized":{"range":[53,10,60,9],"value":{"type":"lambda","lambda":{"patterns":[{"range":[53,11,53,23],"value":{"type":"var","var":{"value":"originalJson"}}},{"range":[53,24,53,43],"value":{"type":"var","var":{"value":"pythonObjectAddress"}}},{"range":[53,44,53,64],"value":{"type":"var","var":{"value":"pythonObjectTypeName"}}},{"range":[53,65,53,86],"value":{"type":"var","var":{"value":"dictEntriesOfInterest"}}},{"range":[53,87,53,95],"value":{"type":"var","var":{"value":"children"}}}],"expression":{"range":[54,13,59,14],"value":{"type":"record","record":[{"range":[54,15,54,42],"value":{"field":{"range":[54,15,54,27],"value":"originalJson"},"expression":{"range":[54,30,54,42],"value":{"type":"functionOrValue","functionOrValue":{"moduleName":[],"name":"originalJson"}}}}},{"range":[55,15,56,13],"value":{"field":{"range":[55,15,55,34],"value":"pythonObjectAddress"},"expression":{"range":[55,37,55,56],"value":{"type":"functionOrValue","functionOrValue":{"moduleName":[],"name":"pythonObjectAddress"}}}}},{"range":[56,15,57,13],"value":{"field":{"range":[56,15,56,35],"value":"pythonObjectTypeName"},"expression":{"range":[56,38,56,58],"value":{"type":"functionOrValue","functionOrValue":{"moduleName":[],"name":"pythonObjectTypeName"}}}}},{"range":[57,15,58,13],"value":{"field":{"range":[57,15,57,36],"value":"dictEntriesOfInterest"},"expression":{"range":[57,39,57,77],"value":{"type":"application","application":[{"range":[57,39,57,60],"value":{"type":"functionOrValue","functionOrValue":{"moduleName":[],"name":"dictEntriesOfInterest"}}},{"range":[57,61,57,63],"value":{"type":"operator","operator":"|>"}},{"range":[57,64,57,77],"value":{"type":"functionOrValue","functionOrValue":{"moduleName":["Dict"],"name":"fromList"}}}]}}}},{"range":[58,15,59,13],"value":{"field":{"range":[58,15,58,23],"value":"children"},"expression":{"range":[58,26,58,74],"value":{"type":"application","application":[{"range":[58,26,58,34],"value":{"type":"functionOrValue","functionOrValue":{"moduleName":[],"name":"children"}}},{"range":[58,35,58,37],"value":{"type":"operator","operator":"|>"}},{"range":[58,38,58,47],"value":{"type":"functionOrValue","functionOrValue":{"moduleName":["Maybe"],"name":"map"}}},{"range":[58,48,58,74],"value":{"type":"parenthesized","parenthesized":{"range":[58,49,58,73],"value":{"type":"application","application":[{"range":[58,49,58,57],"value":{"type":"functionOrValue","functionOrValue":{"moduleName":["List"],"name":"map"}}},{"range":[58,58,58,73],"value":{"type":"functionOrValue","functionOrValue":{"moduleName":[],"name":"UITreeNodeChild"}}}]}}}}]}}}}]}}}}}}},{"range":[61,9,61,26],"value":{"type":"functionOrValue","functionOrValue":{"moduleName":["Json","Decode"],"name":"value"}}},{"range":[62,9,62,69],"value":{"type":"parenthesized","parenthesized":{"range":[62,10,62,68],"value":{"type":"application","application":[{"range":[62,10,62,27],"value":{"type":"functionOrValue","functionOrValue":{"moduleName":["Json","Decode"],"name":"field"}}},{"range":[62,28,62,49],"value":{"type":"literal","literal":"pythonObjectAddress"}},{"range":[62,50,62,68],"value":{"type":"functionOrValue","functionOrValue":{"moduleName":["Json","Decode"],"name":"string"}}}]}}}},{"range":[63,9,63,114],"value":{"type":"parenthesized","parenthesized":{"range":[63,10,63,113],"value":{"type":"application","application":[{"range":[63,10,63,29],"value":{"type":"functionOrValue","functionOrValue":{"moduleName":[],"name":"decodeOptionalField"}}},{"range":[63,30,63,52],"value":{"type":"literal","literal":"pythonObjectTypeName"}},{"range":[63,53,63,71],"value":{"type":"functionOrValue","functionOrValue":{"moduleName":["Json","Decode"],"name":"string"}}},{"range":[63,72,63,74],"value":{"type":"operator","operator":"|>"}},{"range":[63,75,63,90],"value":{"type":"functionOrValue","functionOrValue":{"moduleName":["Json","Decode"],"name":"map"}}},{"range":[63,91,63,113],"value":{"type":"parenthesized","parenthesized":{"range":[63,92,63,112],"value":{"type":"application","application":[{"range":[63,92,63,109],"value":{"type":"functionOrValue","functionOrValue":{"moduleName":["Maybe"],"name":"withDefault"}}},{"range":[63,110,63,112],"value":{"type":"literal","literal":""}}]}}}}]}}}},{"range":[64,9,64,98],"value":{"type":"parenthesized","parenthesized":{"range":[64,10,64,97],"value":{"type":"application","application":[{"range":[64,10,64,27],"value":{"type":"functionOrValue","functionOrValue":{"moduleName":["Json","Decode"],"name":"field"}}},{"range":[64,28,64,51],"value":{"type":"literal","literal":"dictEntriesOfInterest"}},{"range":[64,52,64,97],"value":{"type":"parenthesized","parenthesized":{"range":[64,53,64,96],"value":{"type":"application","application":[{"range":[64,53,64,78],"value":{"type":"functionOrValue","functionOrValue":{"moduleName":["Json","Decode"],"name":"keyValuePairs"}}},{"range":[64,79,64,96],"value":{"type":"functionOrValue","functionOrValue":{"moduleName":["Json","Decode"],"name":"value"}}}]}}}}]}}}},{"range":[65,9,65,111],"value":{"type":"parenthesized","parenthesized":{"range":[65,10,65,110],"value":{"type":"application","application":[{"range":[65,10,65,35],"value":{"type":"functionOrValue","functionOrValue":{"moduleName":[],"name":"decodeOptionalOrNullField"}}},{"range":[65,36,65,46],"value":{"type":"literal","literal":"children"}},{"range":[65,47,65,110],"value":{"type":"parenthesized","parenthesized":{"range":[65,48,65,109],"value":{"type":"application","application":[{"range":[65,48,65,64],"value":{"type":"functionOrValue","functionOrValue":{"moduleName":["Json","Decode"],"name":"list"}}},{"range":[65,65,65,109],"value":{"type":"parenthesized","parenthesized":{"range":[65,66,65,108],"value":{"type":"application","application":[{"range":[65,66,65,82],"value":{"type":"functionOrValue","functionOrValue":{"moduleName":["Json","Decode"],"name":"lazy"}}},{"range":[65,83,65,108],"value":{"type":"parenthesized","parenthesized":{"range":[65,84,65,107],"value":{"type":"lambda","lambda":{"patterns":[{"range":[65,85,65,86],"value":{"type":"all","all":{}}}],"expression":{"range":[65,90,65,107],"value":{"type":"functionOrValue","functionOrValue":{"moduleName":[],"name":"uiTreeNodeDecoder"}}}}}}}}]}}}}]}}}}]}}}}]}}}}}}},{"range":[68,1,71,52],"value":{"type":"function","function":{"documentation":null,"signature":{"range":[68,1,68,93],"value":{"name":{"range":[68,1,68,26],"value":"decodeOptionalOrNullField"},"typeAnnotation":{"range":[68,29,68,93],"value":{"type":"function","function":{"left":{"range":[68,29,68,35],"value":{"type":"typed","typed":{"moduleNameAndName":{"range":[68,29,68,35],"value":{"moduleName":[],"name":"String"}},"args":[]}}},"right":{"range":[68,39,68,93],"value":{"type":"function","function":{"left":{"range":[68,39,68,60],"value":{"type":"typed","typed":{"moduleNameAndName":{"range":[68,39,68,58],"value":{"moduleName":["Json","Decode"],"name":"Decoder"}},"args":[{"range":[68,59,68,60],"value":{"type":"generic","generic":{"value":"a"}}}]}}},"right":{"range":[68,64,68,93],"value":{"type":"typed","typed":{"moduleNameAndName":{"range":[68,64,68,83],"value":{"moduleName":["Json","Decode"],"name":"Decoder"}},"args":[{"range":[68,84,68,93],"value":{"type":"typed","typed":{"moduleNameAndName":{"range":[68,85,68,90],"value":{"moduleName":[],"name":"Maybe"}},"args":[{"range":[68,91,68,92],"value":{"type":"generic","generic":{"value":"a"}}}]}}}]}}}}}}}}}}},"declaration":{"range":[69,1,71,52],"value":{"name":{"range":[69,1,69,26],"value":"decodeOptionalOrNullField"},"arguments":[{"range":[69,27,69,36],"value":{"type":"var","var":{"value":"fieldName"}}},{"range":[69,37,69,44],"value":{"type":"var","var":{"value":"decoder"}}}],"expression":{"range":[70,5,71,52],"value":{"type":"application","application":[{"range":[70,5,70,24],"value":{"type":"functionOrValue","functionOrValue":{"moduleName":[],"name":"decodeOptionalField"}}},{"range":[70,25,70,34],"value":{"type":"functionOrValue","functionOrValue":{"moduleName":[],"name":"fieldName"}}},{"range":[70,35,70,65],"value":{"type":"parenthesized","parenthesized":{"range":[70,36,70,64],"value":{"type":"application","application":[{"range":[70,36,70,56],"value":{"type":"functionOrValue","functionOrValue":{"moduleName":["Json","Decode"],"name":"nullable"}}},{"range":[70,57,70,64],"value":{"type":"functionOrValue","functionOrValue":{"moduleName":[],"name":"decoder"}}}]}}}},{"range":[71,9,71,11],"value":{"type":"operator","operator":"|>"}},{"range":[71,12,71,27],"value":{"type":"functionOrValue","functionOrValue":{"moduleName":["Json","Decode"],"name":"map"}}},{"range":[71,28,71,52],"value":{"type":"parenthesized","parenthesized":{"range":[71,29,71,51],"value":{"type":"application","application":[{"range":[71,29,71,42],"value":{"type":"functionOrValue","functionOrValue":{"moduleName":["Maybe"],"name":"andThen"}}},{"range":[71,43,71,51],"value":{"type":"functionOrValue","functionOrValue":{"moduleName":[],"name":"identity"}}}]}}}}]}}}}}}},{"range":[74,1,90,1],"value":{"type":"function","function":{"documentation":null,"signature":{"range":[74,1,74,87],"value":{"name":{"range":[74,1,74,20],"value":"decodeOptionalField"},"typeAnnotation":{"range":[74,23,74,87],"value":{"type":"function","function":{"left":{"range":[74,23,74,29],"value":{"type":"typed","typed":{"moduleNameAndName":{"range":[74,23,74,29],"value":{"moduleName":[],"name":"String"}},"args":[]}}},"right":{"range":[74,33,74,87],"value":{"type":"function","function":{"left":{"range":[74,33,74,54],"value":{"type":"typed","typed":{"moduleNameAndName":{"range":[74,33,74,52],"value":{"moduleName":["Json","Decode"],"name":"Decoder"}},"args":[{"range":[74,53,74,54],"value":{"type":"generic","generic":{"value":"a"}}}]}}},"right":{"range":[74,58,74,87],"value":{"type":"typed","typed":{"moduleNameAndName":{"range":[74,58,74,77],"value":{"moduleName":["Json","Decode"],"name":"Decoder"}},"args":[{"range":[74,78,74,87],"value":{"type":"typed","typed":{"moduleNameAndName":{"range":[74,79,74,84],"value":{"moduleName":[],"name":"Maybe"}},"args":[{"range":[74,85,74,86],"value":{"type":"generic","generic":{"value":"a"}}}]}}}]}}}}}}}}}}},"declaration":{"range":[75,1,90,1],"value":{"name":{"range":[75,1,75,20],"value":"decodeOptionalField"},"arguments":[{"range":[75,21,75,30],"value":{"type":"var","var":{"value":"fieldName"}}},{"range":[75,31,75,38],"value":{"type":"var","var":{"value":"decoder"}}}],"expression":{"range":[76,5,90,1],"value":{"type":"let","let":{"declarations":[{"range":[77,9,86,5],"value":{"type":"function","function":{"documentation":null,"signature":null,"declaration":{"range":[77,9,85,48],"value":{"name":{"range":[77,9,77,23],"value":"finishDecoding"},"arguments":[{"range":[77,24,77,28],"value":{"type":"var","var":{"value":"json"}}}],"expression":{"range":[78,13,85,48],"value":{"type":"case","case":{"cases":[{"pattern":{"range":[79,17,79,23],"value":{"type":"named","named":{"qualified":{"moduleName":[],"name":"Ok"},"patterns":[{"range":[79,20,79,23],"value":{"type":"var","var":{"value":"val"}}}]}}},"expression":{"range":[81,21,81,79],"value":{"type":"application","application":[{"range":[81,21,81,36],"value":{"type":"functionOrValue","functionOrValue":{"moduleName":["Json","Decode"],"name":"map"}}},{"range":[81,37,81,41],"value":{"type":"functionOrValue","functionOrValue":{"moduleName":[],"name":"Just"}}},{"range":[81,42,81,79],"value":{"type":"parenthesized","parenthesized":{"range":[81,43,81,78],"value":{"type":"application","application":[{"range":[81,43,81,60],"value":{"type":"functionOrValue","functionOrValue":{"moduleName":["Json","Decode"],"name":"field"}}},{"range":[81,61,81,70],"value":{"type":"functionOrValue","functionOrValue":{"moduleName":[],"name":"fieldName"}}},{"range":[81,71,81,78],"value":{"type":"functionOrValue","functionOrValue":{"moduleName":[],"name":"decoder"}}}]}}}}]}}},{"pattern":{"range":[83,17,83,22],"value":{"type":"named","named":{"qualified":{"moduleName":[],"name":"Err"},"patterns":[{"range":[83,21,83,22],"value":{"type":"all","all":{}}}]}}},"expression":{"range":[85,21,85,48],"value":{"type":"application","application":[{"range":[85,21,85,40],"value":{"type":"functionOrValue","functionOrValue":{"moduleName":["Json","Decode"],"name":"succeed"}}},{"range":[85,41,85,48],"value":{"type":"functionOrValue","functionOrValue":{"moduleName":[],"name":"Nothing"}}}]}}}],"expression":{"range":[78,18,78,94],"value":{"type":"application","application":[{"range":[78,18,78,41],"value":{"type":"functionOrValue","functionOrValue":{"moduleName":["Json","Decode"],"name":"decodeValue"}}},{"range":[78,42,78,89],"value":{"type":"parenthesized","parenthesized":{"range":[78,43,78,88],"value":{"type":"application","application":[{"range":[78,43,78,60],"value":{"type":"functionOrValue","functionOrValue":{"moduleName":["Json","Decode"],"name":"field"}}},{"range":[78,61,78,70],"value":{"type":"functionOrValue","functionOrValue":{"moduleName":[],"name":"fieldName"}}},{"range":[78,71,78,88],"value":{"type":"functionOrValue","functionOrValue":{"moduleName":["Json","Decode"],"name":"value"}}}]}}}},{"range":[78,90,78,94],"value":{"type":"functionOrValue","functionOrValue":{"moduleName":[],"name":"json"}}}]}}}}}}}}}}],"expression":{"range":[87,5,88,46],"value":{"type":"application","application":[{"range":[87,5,87,22],"value":{"type":"functionOrValue","functionOrValue":{"moduleName":["Json","Decode"],"name":"value"}}},{"range":[88,9,88,11],"value":{"type":"operator","operator":"|>"}},{"range":[88,12,88,31],"value":{"type":"functionOrValue","functionOrValue":{"moduleName":["Json","Decode"],"name":"andThen"}}},{"range":[88,32,88,46],"value":{"type":"functionOrValue","functionOrValue":{"moduleName":[],"name":"finishDecoding"}}}]}}}}}}}}}}],"comments":[{"range":[84,21,84,61],"value":"-- The field was missing, which is fine!"},{"range":[80,21,80,71],"value":"-- The field is present, so run the decoder on it."}]}